MANIFEST.in
README.txt
requirements.txt
setup.py
ghseet_visualizer.egg-info/PKG-INFO
ghseet_visualizer.egg-info/SOURCES.txt
ghseet_visualizer.egg-info/dependency_links.txt
ghseet_visualizer.egg-info/requires.txt
ghseet_visualizer.egg-info/top_level.txt
gsheetvisualizer/__init__.py